redquill/__init__.py
redquill/core/__init__.py
redquill/core/redquill.py
redquill/test/__init__.py
redquill/test/test_redquill.py
redquill-0.0.1.dist-info/LICENSE
redquill-0.0.1.dist-info/METADATA
redquill-0.0.1.dist-info/WHEEL
redquill-0.0.1.dist-info/top_level.txt
redquill-0.0.1.dist-info/RECORD
