Metadata-Version: 2.1
Name: redquill
Version: 0.0.1
Summary: Logging for pandas and more.
Home-page: https://github.com/vincentzhchen/redquill
Author: Vincent Chen
Author-email: vincent.zh.chen@gmail.com
License: Apache 2.0
Project-URL: Source, https://github.com/vincentzhchen/redquill
Platform: UNKNOWN
Classifier: License :: OSI Approved :: Apache Software License
Classifier: Development Status :: 4 - Beta
Classifier: Programming Language :: Python :: 3.6
Classifier: Programming Language :: Python :: 3.7
Classifier: Topic :: System :: Logging
Requires-Python: >=3.6
Requires-Dist: pandas (>=0.18.0)
